apicrusher/__init__.py
apicrusher/core.py
apicrusher/model_availability.py
apicrusher-2.2.1.dist-info/METADATA
apicrusher-2.2.1.dist-info/WHEEL
apicrusher-2.2.1.dist-info/top_level.txt
apicrusher-2.2.1.dist-info/RECORD
