Metadata-Version: 2.4
Name: apicrusher
Version: 2.2.1
Summary: Cut AI API costs by 63-99% with intelligent routing across all AI providers
Home-page: https://apicrusher.com
Author: APICrusher
Author-email: hello@apicrusher.com
License: MIT
Project-URL: Website, https://apicrusher.com
Project-URL: Documentation, https://apicrusher.com/documentation
Project-URL: Changelog, https://pypi.org/project/apicrusher/
Keywords: openai,anthropic,google,ai,api,optimization,cost-reduction,llm,gpt,claude,gemini,gpt-5,gpt-4,claude-4,api-optimization,ai-cost-reduction,universal-ai,groq,mistral,cohere,deepseek,llama
Platform: any
Classifier: Programming Language :: Python :: 3
Classifier: Programming Language :: Python :: 3.7
Classifier: Programming Language :: Python :: 3.8
Classifier: Programming Language :: Python :: 3.9
Classifier: Programming Language :: Python :: 3.10
Classifier: Programming Language :: Python :: 3.11
Classifier: Programming Language :: Python :: 3.12
Classifier: License :: OSI Approved :: MIT License
Classifier: Operating System :: OS Independent
Classifier: Development Status :: 5 - Production/Stable
Classifier: Intended Audience :: Developers
Classifier: Topic :: Software Development :: Libraries :: Python Modules
Classifier: Topic :: Scientific/Engineering :: Artificial Intelligence
Requires-Python: >=3.7
Requires-Dist: requests>=2.28.0
Provides-Extra: openai
Requires-Dist: openai>=1.0.0; extra == "openai"
Provides-Extra: anthropic
Requires-Dist: anthropic>=0.25.0; extra == "anthropic"
Provides-Extra: google
Requires-Dist: google-generativeai>=0.3.0; extra == "google"
Provides-Extra: cohere
Requires-Dist: cohere>=4.0.0; extra == "cohere"
Provides-Extra: redis
Requires-Dist: redis>=4.5.0; extra == "redis"
Provides-Extra: standard
Requires-Dist: openai>=1.0.0; extra == "standard"
Requires-Dist: redis>=4.5.0; extra == "standard"
Provides-Extra: all
Requires-Dist: openai>=1.0.0; extra == "all"
Requires-Dist: anthropic>=0.25.0; extra == "all"
Requires-Dist: google-generativeai>=0.3.0; extra == "all"
Requires-Dist: cohere>=4.0.0; extra == "all"
Requires-Dist: redis>=4.5.0; extra == "all"
Provides-Extra: dev
Requires-Dist: pytest>=7.0.0; extra == "dev"
Requires-Dist: black>=22.0.0; extra == "dev"
Requires-Dist: flake8>=4.0.0; extra == "dev"
Requires-Dist: twine>=4.0.0; extra == "dev"
Requires-Dist: wheel>=0.37.0; extra == "dev"
Dynamic: author
Dynamic: author-email
Dynamic: classifier
Dynamic: description
Dynamic: description-content-type
Dynamic: home-page
Dynamic: keywords
Dynamic: license
Dynamic: platform
Dynamic: project-url
Dynamic: provides-extra
Dynamic: requires-dist
Dynamic: requires-python
Dynamic: summary
